LICENSE.md
README.md
setup.py
lazop_sdk/__init__.py
lazop_sdk/base.py
lazop_sdk_rahmadafandi.egg-info/PKG-INFO
lazop_sdk_rahmadafandi.egg-info/SOURCES.txt
lazop_sdk_rahmadafandi.egg-info/dependency_links.txt
lazop_sdk_rahmadafandi.egg-info/requires.txt
lazop_sdk_rahmadafandi.egg-info/top_level.txt