Metadata-Version: 2.1
Name: lazop-sdk-rahmadafandi
Version: 1.0.3
Summary: Lazada Official SDK
Home-page: https://github.com/yomaaf/lazop-sdk
Author: Pongsakorn
Author-email: pongsakorn.psks@gmail.com
License: README.md
Platform: UNKNOWN
Classifier: License :: OSI Approved :: MIT License
Classifier: Programming Language :: Python :: 3
Classifier: Programming Language :: Python :: 3.7
License-File: LICENSE.md
